async_foaas.py
async_foaas-0.4.0.dist-info/LICENSE
async_foaas-0.4.0.dist-info/METADATA
async_foaas-0.4.0.dist-info/WHEEL
async_foaas-0.4.0.dist-info/top_level.txt
async_foaas-0.4.0.dist-info/RECORD
